ocsf/api/__init__.py
ocsf/api/client.py
ocsf/api/py.typed
ocsf/compare/__init__.py
ocsf/compare/__main__.py
ocsf/compare/compare.py
ocsf/compare/factory.py
ocsf/compare/formatter.py
ocsf/compare/model.py
ocsf/compare/py.typed
ocsf/compile/NOTES.md
ocsf/compile/README.md
ocsf/compile/__init__.py
ocsf/compile/__main__.py
ocsf/compile/compiler.py
ocsf/compile/debug.py
ocsf/compile/merge.py
ocsf/compile/options.py
ocsf/compile/planners/annotations.py
ocsf/compile/planners/category_events.py
ocsf/compile/planners/datetime.py
ocsf/compile/planners/dictionary.py
ocsf/compile/planners/extends.py
ocsf/compile/planners/extension.py
ocsf/compile/planners/include.py
ocsf/compile/planners/object_type.py
ocsf/compile/planners/observable.py
ocsf/compile/planners/planner.py
ocsf/compile/planners/profile.py
ocsf/compile/planners/py.typed
ocsf/compile/planners/set_category.py
ocsf/compile/planners/uid.py
ocsf/compile/planners/uid_names.py
ocsf/compile/protoschema.py
ocsf/compile/py.typed
ocsf/repository/README.md
ocsf/repository/__init__.py
ocsf/repository/definitions.py
ocsf/repository/helpers.py
ocsf/repository/py.typed
ocsf/repository/reader.py
ocsf/repository/repository.py
ocsf/schema/__init__.py
ocsf/schema/__main__.py
ocsf/schema/json.py
ocsf/schema/model.py
ocsf/schema/py.typed
ocsf/util/__init__.py
ocsf/util/get_schema.py
ocsf/util/py.typed
ocsf/validate/compatibility/__init__.py
ocsf/validate/compatibility/__main__.py
ocsf/validate/compatibility/added_required_attrs.py
ocsf/validate/compatibility/changed_type.py
ocsf/validate/compatibility/context.py
ocsf/validate/compatibility/example.toml
ocsf/validate/compatibility/increased_requirement.py
ocsf/validate/compatibility/py.typed
ocsf/validate/compatibility/removed_records.py
ocsf/validate/compatibility/removed_uids.py
ocsf/validate/compatibility/validator.py
ocsf/validate/framework/__init__.py
ocsf/validate/framework/formatting.py
ocsf/validate/framework/py.typed
ocsf/validate/framework/summarize.py
ocsf_lib-0.10.4.dist-info/LICENSE
ocsf_lib-0.10.4.dist-info/METADATA
ocsf_lib-0.10.4.dist-info/WHEEL
ocsf_lib-0.10.4.dist-info/entry_points.txt
ocsf_lib-0.10.4.dist-info/RECORD
